fabric_compute_sdk-1.1.0.dist-info/licenses/LICENSE
fabric_sdk/__init__.py
fabric_sdk/client.py
fabric_sdk/exceptions.py
fabric_sdk/types.py
fabric_sdk/world_state.py
fabric_compute_sdk-1.1.0.dist-info/METADATA
fabric_compute_sdk-1.1.0.dist-info/WHEEL
fabric_compute_sdk-1.1.0.dist-info/top_level.txt
fabric_compute_sdk-1.1.0.dist-info/RECORD
