Metadata-Version: 2.4
Name: fabric-compute-sdk
Version: 1.1.0
Summary: Official Python SDK for Fabric - Distributed AI Compute Network
Home-page: https://github.com/Carmel-Labs-Inc/fabric-sdk
Author: Carmel Labs, Inc.
Author-email: "Carmel Labs, Inc." <support@carmel.so>
License: Apache-2.0
Project-URL: Homepage, https://fabric.carmel.so
Project-URL: Documentation, https://docs.fabric.carmel.so
Project-URL: Repository, https://github.com/Carmel-Labs-Inc/fabric-sdk
Project-URL: Bug Tracker, https://github.com/Carmel-Labs-Inc/fabric-sdk/issues
Keywords: ai,compute,distributed,gpu,machine-learning,pytorch
Classifier: Development Status :: 4 - Beta
Classifier: Intended Audience :: Developers
Classifier: Topic :: Software Development :: Libraries :: Python Modules
Classifier: License :: OSI Approved :: Apache Software License
Classifier: Programming Language :: Python :: 3
Classifier: Programming Language :: Python :: 3.8
Classifier: Programming Language :: Python :: 3.9
Classifier: Programming Language :: Python :: 3.10
Classifier: Programming Language :: Python :: 3.11
Classifier: Programming Language :: Python :: 3.12
Requires-Python: >=3.8
License-File: LICENSE
Requires-Dist: requests>=2.31.0
Provides-Extra: dev
Requires-Dist: pytest>=7.4.0; extra == "dev"
Requires-Dist: black>=23.7.0; extra == "dev"
Requires-Dist: mypy>=1.5.0; extra == "dev"
Dynamic: author
Dynamic: home-page
Dynamic: license-file
Dynamic: requires-python
